printclean/__init__.py
printclean/clean.py
printclean/perspective.py
printclean/utils.py
printclean-1.1.0.dist-info/LICENSE
printclean-1.1.0.dist-info/METADATA
printclean-1.1.0.dist-info/WHEEL
printclean-1.1.0.dist-info/entry_points.txt
printclean-1.1.0.dist-info/top_level.txt
printclean-1.1.0.dist-info/RECORD
