Metadata-Version: 2.1
Name: printclean
Version: 1.1.0
Summary: Cleans photographed documents for improved printing
Home-page: https://github.com/danmysak/print-clean
Author: Danylo Mysak
Author-email: danmysak@gmail.com
Project-URL: Bug Tracker, https://github.com/danmysak/print-clean/issues
Classifier: Programming Language :: Python :: 3
Classifier: License :: OSI Approved :: MIT License
Classifier: Operating System :: OS Independent
Requires-Python: >=3.9
License-File: LICENSE
Requires-Dist: numpy
Requires-Dist: opencv-python
Requires-Dist: pytesseract
Requires-Dist: scikit-image
